README.md
setup.py
s3/__init__.py
s3/clf.py
s3/frame.py
s3/funcs.py
s34me.egg-info/PKG-INFO
s34me.egg-info/SOURCES.txt
s34me.egg-info/dependency_links.txt
s34me.egg-info/requires.txt
s34me.egg-info/top_level.txt