Metadata-Version: 1.0
Name: s34me
Version: 0.1.6
Summary: s34me is a high-level wrapper for handling s3 objects in boto3 and Pandas
Home-page: https://github.com/yinleon/s3
Author: leon yin
Author-email: UNKNOWN
License: MIT
Keywords: aws s3 boto3 pandas dataframe
Platform: UNKNOWN
